afplay_win/__init__.py
afplay_win/__main__.py
afplay_win/cli.py
afplay_win-0.0.1.dist-info/LICENSE
afplay_win-0.0.1.dist-info/METADATA
afplay_win-0.0.1.dist-info/WHEEL
afplay_win-0.0.1.dist-info/entry_points.txt
afplay_win-0.0.1.dist-info/top_level.txt
afplay_win-0.0.1.dist-info/RECORD
