Metadata-Version: 2.1
Name: afplay-win
Version: 0.0.1
Summary: Tiny utility that mimics 'afplay' in windows
Author: Sukhbinder Singh
License: Apache-2.0
Project-URL: Homepage, https://github.com/sukhbinder/afplay-win
Project-URL: Changelog, https://github.com/sukhbinder/afplay-win/releases
Project-URL: Issues, https://github.com/sukhbinder/afplay-win/issues
Project-URL: CI, https://github.com/sukhbinder/afplay-win/actions
Classifier: License :: OSI Approved :: Apache Software License
Requires-Python: >=3.8
License-File: LICENSE
Provides-Extra: test
Requires-Dist: pytest; extra == "test"
